<?xml version="1.0" ?><annotation>
	<folder>0-150</folder>
	<filename>84.jpg</filename>
	<path>C:/Users/BT/Desktop/0-150/84.jpg</path>
	<source>
		<database>Unknown</database>
	</source>
	<size>
		<width>520</width>
		<height>212</height>
		<depth>3</depth>
	</size>
	<segmented>0</segmented>
	<object>
		<name>ad</name>
		<pose>Unspecified</pose>
		<truncated>0</truncated>
		<difficult>0</difficult>
		<bndbox>
			<xmin>25</xmin>
			<ymin>46</ymin>
			<xmax>94</xmax>
			<ymax>141</ymax>
		</bndbox>
	</object>
	<object>
		<name>ag</name>
		<pose>Unspecified</pose>
		<truncated>0</truncated>
		<difficult>0</difficult>
		<bndbox>
			<xmin>121</xmin>
			<ymin>59</ymin>
			<xmax>168</xmax>
			<ymax>147</ymax>
		</bndbox>
	</object>
	<object>
		<name>ab</name>
		<pose>Unspecified</pose>
		<truncated>0</truncated>
		<difficult>0</difficult>
		<bndbox>
			<xmin>186</xmin>
			<ymin>59</ymin>
			<xmax>242</xmax>
			<ymax>142</ymax>
		</bndbox>
	</object>
	<object>
		<name>ae</name>
		<pose>Unspecified</pose>
		<truncated>0</truncated>
		<difficult>0</difficult>
		<bndbox>
			<xmin>258</xmin>
			<ymin>57</ymin>
			<xmax>319</xmax>
			<ymax>129</ymax>
		</bndbox>
	</object>
	<object>
		<name>ae</name>
		<pose>Unspecified</pose>
		<truncated>0</truncated>
		<difficult>0</difficult>
		<bndbox>
			<xmin>317</xmin>
			<ymin>50</ymin>
			<xmax>376</xmax>
			<ymax>140</ymax>
		</bndbox>
	</object>
	<object>
		<name>f</name>
		<pose>Unspecified</pose>
		<truncated>0</truncated>
		<difficult>0</difficult>
		<bndbox>
			<xmin>377</xmin>
			<ymin>55</ymin>
			<xmax>445</xmax>
			<ymax>167</ymax>
		</bndbox>
	</object>
</annotation>